slack_secret/__init__.py
slack_secret/channels.py
slack_secret/lib.py
slack_secret/main.py
slack_secret/users.py
slack_secret-0.2.1.dist-info/entry_points.txt
slack_secret-0.2.1.dist-info/LICENSE
slack_secret-0.2.1.dist-info/WHEEL
slack_secret-0.2.1.dist-info/METADATA
slack_secret-0.2.1.dist-info/RECORD
