Metadata-Version: 2.1
Name: slack-secret
Version: 0.2.1
Summary: A tool to backup and delete the content of private slack channels
Home-page: https://github.com/niparis/slack-secret
Author: Nicolas Paris
Author-email: ni.paris@gmail.com
Requires-Python: >=3.8,<4.0
Classifier: Programming Language :: Python :: 3
Classifier: Programming Language :: Python :: 3.8
Classifier: Topic :: Software Development :: Libraries :: Python Modules
Requires-Dist: slackclient (>=2.6.2,<3.0.0)
Requires-Dist: tqdm (>=4.46.0,<5.0.0)
Project-URL: Repository, https://github.com/niparis/slack-secret
